writefile/__init__.py
writefile/main.py
writefile/tests/__init__.py
writefile-0.1.dist-info/DESCRIPTION.rst
writefile-0.1.dist-info/METADATA
writefile-0.1.dist-info/RECORD
writefile-0.1.dist-info/WHEEL
writefile-0.1.dist-info/entry_points.txt
writefile-0.1.dist-info/metadata.json
writefile-0.1.dist-info/top_level.txt
