Metadata-Version: 2.0
Name: writefile
Version: 0.1
Summary: Write stdin to a given path, creating directories as necessary.
Home-page: https://github.com/nejucomo/writefile
Author: Nathan Wilcox
Author-email: nejucomo@gmail.com
License: GPLv3
Platform: UNKNOWN
